localplan/__init__.py
localplan/localplan.py
localplan-0.0.2.dist-info/LICENSE
localplan-0.0.2.dist-info/METADATA
localplan-0.0.2.dist-info/WHEEL
localplan-0.0.2.dist-info/top_level.txt
localplan-0.0.2.dist-info/RECORD
