Metadata-Version: 2.1
Name: localplan
Version: 0.0.2
Summary: python tool for local area energy planning
Home-page: https://github.com/elgenied/localplan
Author: Elgenied Elqurashi
Author-email: e.elqurashi@surrey.ac.uk
License: MIT license
Keywords: localplan
Classifier: Development Status :: 2 - Pre-Alpha
Classifier: Intended Audience :: Developers
Classifier: License :: OSI Approved :: MIT License
Classifier: Natural Language :: English
Classifier: Programming Language :: Python :: 3
Classifier: Programming Language :: Python :: 3.7
Classifier: Programming Language :: Python :: 3.8
Classifier: Programming Language :: Python :: 3.9
Classifier: Programming Language :: Python :: 3.10
Requires-Python: >=3.7
License-File: LICENSE
